snagboot-2.5.dist-info/licenses/LICENSE
snagfactory/__init__.py
snagfactory/board.py
snagfactory/config.kv
snagfactory/config.py
snagfactory/fastboot.py
snagfactory/gui-requirements.txt
snagfactory/gui.kv
snagfactory/gui.py
snagfactory/session.py
snagfactory/utils.py
snagfactory/assets/boards.png
snagfactory/assets/config.png
snagfactory/assets/lab_penguins.ico
snagfactory/assets/lab_penguins.png
snagfactory/assets/load_config.png
snagfactory/assets/rescan.png
snagfactory/assets/save.png
snagfactory/assets/start.png
snagfactory/assets/stop.png
snagfactory/assets/view_logs.png
snagflash/__init__.py
snagflash/cli.py
snagflash/dfu.py
snagflash/fastboot.py
snagflash/fastboot_uboot.py
snagflash/ums.py
snagflash/android_sparse_file/__init__.py
snagflash/android_sparse_file/sparse.py
snagflash/android_sparse_file/utils.py
snagflash/bmaptools/BmapCopy.py
snagflash/bmaptools/BmapCreate.py
snagflash/bmaptools/BmapHelpers.py
snagflash/bmaptools/Filemap.py
snagflash/bmaptools/__init__.py
snagrecover/50-snagboot.rules
snagrecover/__init__.py
snagrecover/am335x_usb_setup.sh
snagrecover/cli.py
snagrecover/config.py
snagrecover/prompt.ps1
snagrecover/supported_socs.yaml
snagrecover/usb.py
snagrecover/utils.py
snagrecover/firmware/__init__.py
snagrecover/firmware/am335x_fw.py
snagrecover/firmware/amlogic_fw.py
snagrecover/firmware/bcm.py
snagrecover/firmware/firmware.py
snagrecover/firmware/imx_fw.py
snagrecover/firmware/ivt.py
snagrecover/firmware/rom_container.py
snagrecover/firmware/sama5_fw.py
snagrecover/firmware/samba_applet.py
snagrecover/firmware/zynqmp_fw.py
snagrecover/firmware/sunxi_fw/__init__.py
snagrecover/firmware/sunxi_fw/fel-to-spl-thunk.S
snagrecover/firmware/sunxi_fw/fel-to-spl-thunk.bin
snagrecover/firmware/sunxi_fw/mmu.py
snagrecover/firmware/sunxi_fw/soc_info.yaml
snagrecover/firmware/sunxi_fw/sunxi_fw.py
snagrecover/protocols/__init__.py
snagrecover/protocols/amlogic.py
snagrecover/protocols/bcm.py
snagrecover/protocols/bootp.py
snagrecover/protocols/dfu.py
snagrecover/protocols/fastboot.py
snagboot-2.5.dist-info/METADATA
snagboot-2.5.dist-info/WHEEL
snagboot-2.5.dist-info/entry_points.txt
snagboot-2.5.dist-info/top_level.txt
snagboot-2.5.dist-info/RECORD
