Metadata-Version: 2.4
Name: snagboot
Version: 2.5
Summary: Generic recovery and reflashing tool for embedded platforms
Author-email: Romain Gantois <romain.gantois@bootlin.com>
License-Expression: GPL-2.0-only
Project-URL: Source Code, https://github.com/bootlin/snagboot
Classifier: Programming Language :: Python :: 3
Classifier: Operating System :: POSIX :: Linux
Classifier: Operating System :: Microsoft :: Windows :: Windows 10
Classifier: Operating System :: Microsoft :: Windows :: Windows 11
Requires-Python: >=3.9
License-File: LICENSE
Requires-Dist: pyyaml>=6.0
Requires-Dist: pyusb>=1.2.1
Requires-Dist: pyserial>=3.5
Requires-Dist: xmodem>=0.4.6
Requires-Dist: tftpy>=0.8.2
Requires-Dist: crccheck>=1.3.0
Requires-Dist: pylibfdt>=1.7.2.post1
Requires-Dist: packaging>=24.2
Requires-Dist: pyfatfs>=1.1.0
Provides-Extra: gui
Requires-Dist: kivy==2.3.1; extra == "gui"
Dynamic: license-file
